a1/cpu.v
`timescale 1ps/1ps
module main();

    initial begin
        $dumpfile("cpu.vcd");
        $dumpvars(1,main);
    end

    // clock
    wire clk;
    clock c0(clk);

    // PC
    reg [15:0]pc = 16'h0000;

    // registers
    reg [15:0]regs[15:0];

    wire [15:0]inst;

    //define our opcodes
    reg [3:0] opcode ;//= inst[15:12];
   
//    reg [7:0] j; 
    imem i0(pc,inst);

    reg [15:0] cycle = 0;

    
    always @(posedge clk) begin
        
        //grab the opcode 
        opcode = inst[15:12];
 
        /* stop after 20 cycles */
        if (cycle == 20) $finish;
  

        /* if jump instruction given */
        if (opcode == 2) begin
             //$display("jump");
             pc <=inst[12:0];
             //pc <= j;
        end

        /* if add instruction given */
        if (opcode == 1) begin
             //$display("add");
             regs[inst[3:0]] <= regs[inst[11:8]] + regs[inst[7:4]];
        end
        /* if move instruction given */
        if(opcode == 0) begin
             //$display("move");
            regs[inst[3:0]] <= inst[11:4];
        end
        
        
        $display("cycle=%d, pc=%x, inst=%x, regs=%x:%x:%x:%x:%x:%x:%x:%x:%x:%x:%x:%x:%x:%x:%x:%x",cycle,pc,inst,
            regs[0], regs[1], regs[2], regs[3], regs[4], regs[5], regs[6], regs[7],
            regs[8], regs[9], regs[10], regs[11], regs[12], regs[13], regs[14], regs[15]);
        cycle <= cycle + 1;
        
        
        if (opcode !=2)  pc <= pc + 1;
    end

endmodule

/* clock */
module clock(output clk);
    reg theClock = 1;

    assign clk = theClock;
    
    always begin
        #5;
        theClock = !theClock;
    end
endmodule

/* instruction memory */
module imem(input [15:0]raddr, output [15:0]data);
    reg [15:0]mem[15:0];

    /* Simulation -- read initial content from file */
    initial begin
        $readmemh("imem.hex",mem,0,6);
    end

    assign data = mem[raddr];
endmodule

a1/cpu.vcd
$date
	Thu Feb  5 23:21:48 2015
$end
$version
	Icarus Verilog
$end
$timescale
	1ps
$end
$scope module main $end
$var wire 16 ! inst [15:0] $end
$var wire 1 " clk $end
$var reg 16 # cycle [15:0] $end
$var reg 4 $ opcode [3:0] $end
$var reg 16 % pc [15:0] $end
$upscope $end
$enddefinitions $end
#0
$dumpvars
b0 %
bx $
b0 #
1"
b0 !
$end
#5
0"
#10
b10001 !
b1 %
b1 #
b0 $
1"
#15
0"
#20
b100010 !
b10 %
b10 #
1"
#25
0"
#30
b110011 !
b11 %
b11 #
1"
#35
0"
#40
b1000100 !
b100 %
b100 #
1"
#45
0"
#50
b1000100100010 !
b101 %
b101 #
1"
#55
0"
#60
b10000000000101 !
b110 %
b110 #
b1 $
1"
#65
0"
#70
b111 #
b1000100100010 !
b101 %
b10 $
1"
#75
0"
#80
b10000000000101 !
b110 %
b1000 #
b1 $
1"
#85
0"
#90
b1001 #
b1000100100010 !
b101 %
b10 $
1"
#95
0"
#100
b10000000000101 !
b110 %
b1010 #
b1 $
1"
#105
0"
#110
b1011 #
b1000100100010 !
b101 %
b10 $
1"
#115
0"
#120
b10000000000101 !
b110 %
b1100 #
b1 $
1"
#125
0"
#130
b1101 #
b1000100100010 !
b101 %
b10 $
1"
#135
0"
#140
b10000000000101 !
b110 %
b1110 #
b1 $
1"
#145
0"
#150
b1111 #
b1000100100010 !
b101 %
b10 $
1"
#155
0"
#160
b10000000000101 !
b110 %
b10000 #
b1 $
1"
#165
0"
#170
b10001 #
b1000100100010 !
b101 %
b10 $
1"
#175
0"
#180
b10000000000101 !
b110 %
b10010 #
b1 $
1"
#185
0"
#190
b10011 #
b1000100100010 !
b101 %
b10 $
1"
#195
0"
#200
b10000000000101 !
b110 %
b10100 #
b1 $
1"
#205
0"
#210
b10 $
1"
